ollin/__init__.py
ollin/version.py
ollin/calibration/__init__.py
ollin/calibration/calibrate.py
ollin/calibration/config.py
ollin/calibration/home_range.py
ollin/calibration/occupancy.py
ollin/calibration/velocity.py
ollin/core/__init__.py
ollin/core/constants.py
ollin/core/detection.py
ollin/core/home_range.py
ollin/core/movement.py
ollin/core/occupancy.py
ollin/core/sites.py
ollin/core/utils.py
ollin/estimation/__init__.py
ollin/estimation/estimation.py
ollin/estimation/stanmodels.py
ollin/estimation/occupancy/__init__.py
ollin/estimation/occupancy/base.py
ollin/estimation/occupancy/naive.py
ollin/estimation/occupancy/occupancy_estimation.py
ollin/estimation/occupancy/single_species.py
ollin/estimation/occupancy/voronoi_areas.py
ollin/movement_analyzers/__init__.py
ollin/movement_analyzers/base.py
ollin/movement_analyzers/bearing.py
ollin/movement_analyzers/turn_angle.py
ollin/movement_analyzers/velocity.py
ollin/movement_models/__init__.py
ollin/movement_models/base.py
ollin/movement_models/basemodel.py
ollin/movement_models/constant_brownian.py
ollin/movement_models/constant_levy.py
ollin/movement_models/gradient_brownian.py
ollin/movement_models/gradient_levy.py
ollin/movement_models/variable_brownian.py
ollin/movement_models/variable_levy.py
ollin-0.1.0.dist-info/METADATA
ollin-0.1.0.dist-info/RECORD
ollin-0.1.0.dist-info/WHEEL
ollin-0.1.0.dist-info/top_level.txt
test/__init__.py
test/test_sample.py
test/test_sites.py
