Metadata-Version: 2.1
Name: ollin
Version: 0.1.0
Summary: Animal Motion Simulator
Home-page: https://github.com/mbsantiago/ollin
Author: CONABIO, Santiago Martínez
Author-email: santiago.mbal@gmail.com
License: UNKNOWN
Platform: UNKNOWN
Classifier: Programming Language :: Python :: 3
Classifier: Programming Language :: Python :: 2.7
Classifier: Topic :: Scientific/Engineering :: Bio-Informatics
Classifier: Development Status :: 3 - Alpha
Classifier: License :: OSI Approved :: GNU General Public License v3 (GPLv3)
Classifier: Operating System :: OS Independent
Classifier: Intended Audience :: Science/Research
Requires-Dist: pystan
Requires-Dist: six
Requires-Dist: numpy
Requires-Dist: numba
Requires-Dist: scipy
Requires-Dist: backports.functools-lru-cache
